dockrion_adapters/__init__.py
dockrion_adapters/base.py
dockrion_adapters/errors.py
dockrion_adapters/handler_adapter.py
dockrion_adapters/langgraph_adapter.py
dockrion_adapters/registry.py
dockrion_cli/build_cmd.py
dockrion_cli/deploy_cmd.py
dockrion_cli/info_cmd.py
dockrion_cli/init_cmd.py
dockrion_cli/logs_cmd.py
dockrion_cli/main.py
dockrion_cli/run_cmd.py
dockrion_cli/test_cmd.py
dockrion_cli/utils.py
dockrion_cli/validate_cmd.py
dockrion_common/__init__.py
dockrion_common/auth_utils.py
dockrion_common/constants.py
dockrion_common/env_utils.py
dockrion_common/errors.py
dockrion_common/http_models.py
dockrion_common/logger.py
dockrion_common/path_utils.py
dockrion_common/validation.py
dockrion_policy/policy_engine.py
dockrion_policy/redactor.py
dockrion_policy/tool_guard.py
dockrion_runtime/__init__.py
dockrion_runtime/app.py
dockrion_runtime/config.py
dockrion_runtime/metrics.py
dockrion_runtime/openapi.py
dockrion_runtime/policies.py
dockrion_runtime/schema_utils.py
dockrion_runtime/auth/__init__.py
dockrion_runtime/auth/api_key.py
dockrion_runtime/auth/base.py
dockrion_runtime/auth/context.py
dockrion_runtime/auth/exceptions.py
dockrion_runtime/auth/factory.py
dockrion_runtime/auth/jwt_handler.py
dockrion_runtime/endpoints/__init__.py
dockrion_runtime/endpoints/health.py
dockrion_runtime/endpoints/info.py
dockrion_runtime/endpoints/invoke.py
dockrion_runtime/endpoints/welcome.py
dockrion_runtime/static/dockrion-logo.png
dockrion_schema/__init__.py
dockrion_schema/dockfile_v1.py
dockrion_schema/json_schema.py
dockrion_schema/serialization.py
dockrion_sdk/__init__.py
dockrion_sdk/client.py
dockrion_sdk/core/__init__.py
dockrion_sdk/core/invoker.py
dockrion_sdk/core/loader.py
dockrion_sdk/core/validate.py
dockrion_sdk/deployment/__init__.py
dockrion_sdk/deployment/deploy.py
dockrion_sdk/deployment/docker.py
dockrion_sdk/deployment/pypi_server.py
dockrion_sdk/deployment/runtime_gen.py
dockrion_sdk/remote/__init__.py
dockrion_sdk/remote/controller.py
dockrion-0.0.2.dist-info/METADATA
dockrion-0.0.2.dist-info/WHEEL
dockrion-0.0.2.dist-info/entry_points.txt
dockrion-0.0.2.dist-info/top_level.txt
dockrion-0.0.2.dist-info/RECORD
