Metadata-Version: 2.4
Name: dockrion
Version: 0.0.2
Summary: Dockrion - Deploy and manage AI agents with ease
Author-email: Paritosh Sharma <paritoshsharma0707@gmail.com>, Prakhar Agarwal <prakhara56@gmail.com>
License-Expression: Apache-2.0
Project-URL: Homepage, https://github.com/paritosh0707/Dockrion
Project-URL: Repository, https://github.com/paritosh0707/Dockrion
Project-URL: Documentation, https://github.com/paritosh0707/Dockrion#readme
Project-URL: Issues, https://github.com/paritosh0707/Dockrion/issues
Keywords: ai,agents,deployment,langgraph,langchain,dockrion,llm
Classifier: Development Status :: 3 - Alpha
Classifier: Environment :: Console
Classifier: Intended Audience :: Developers
Classifier: Programming Language :: Python :: 3.11
Classifier: Programming Language :: Python :: 3.12
Classifier: Topic :: Software Development :: Libraries :: Python Modules
Classifier: Topic :: Scientific/Engineering :: Artificial Intelligence
Requires-Python: >=3.11
Requires-Dist: typer>=0.12.0
Requires-Dist: rich>=13.7.0
Requires-Dist: pyyaml>=6.0
Requires-Dist: requests>=2.31
Requires-Dist: jinja2>=3.1.0
Requires-Dist: pydantic>=2.5
Provides-Extra: langgraph
Requires-Dist: langgraph>=0.0.20; extra == "langgraph"
Requires-Dist: langchain-core>=0.1.0; extra == "langgraph"
Provides-Extra: langchain
Requires-Dist: langchain>=0.1.0; extra == "langchain"
Requires-Dist: langchain-core>=0.1.0; extra == "langchain"
Provides-Extra: runtime
Requires-Dist: fastapi>=0.109.0; extra == "runtime"
Requires-Dist: uvicorn[standard]>=0.27.0; extra == "runtime"
Requires-Dist: prometheus-client>=0.20; extra == "runtime"
Provides-Extra: jwt
Requires-Dist: PyJWT[crypto]>=2.8.0; extra == "jwt"
Provides-Extra: all
Requires-Dist: dockrion[jwt,langchain,langgraph,runtime]; extra == "all"
